LICENSE.txt
MANIFEST.in
README.rst
pyproject.toml
setup.cfg
rxsci/__init__.py
rxsci/run.py
rxsci.egg-info/PKG-INFO
rxsci.egg-info/SOURCES.txt
rxsci.egg-info/dependency_links.txt
rxsci.egg-info/requires.txt
rxsci.egg-info/top_level.txt
rxsci/compression/__init__.py
rxsci/compression/z.py
rxsci/compression/zstd.py
rxsci/container/__init__.py
rxsci/container/csv.py
rxsci/container/json.py
rxsci/container/parquet.py
rxsci/data/__init__.py
rxsci/data/batch.py
rxsci/data/cache.py
rxsci/data/clip.py
rxsci/data/codec.py
rxsci/data/fill_none.py
rxsci/data/lag.py
rxsci/data/pad.py
rxsci/data/roll.py
rxsci/data/sort.py
rxsci/data/split.py
rxsci/data/time_split.py
rxsci/data/to_array.py
rxsci/data/to_deque.py
rxsci/data/to_list.py
rxsci/data/train_test_split.py
rxsci/error/__init__.py
rxsci/error/ignore.py
rxsci/error/map.py
rxsci/error/router.py
rxsci/framing/__init__.py
rxsci/framing/length_prefix.py
rxsci/framing/line.py
rxsci/internal/__init__.py
rxsci/internal/utils.py
rxsci/io/__init__.py
rxsci/io/file.py
rxsci/io/walk.py
rxsci/math/__init__.py
rxsci/math/max.py
rxsci/math/mean.py
rxsci/math/min.py
rxsci/math/stddev.py
rxsci/math/sum.py
rxsci/math/variance.py
rxsci/math/dist/__init__.py
rxsci/math/formal/__init__.py
rxsci/math/formal/stddev.py
rxsci/math/formal/variance.py
rxsci/mux/__init__.py
rxsci/mux/muxconnectable.py
rxsci/mux/muxobservable.py
rxsci/mux/muxobserver.py
rxsci/operators/__init__.py
rxsci/operators/assert_.py
rxsci/operators/count.py
rxsci/operators/distinct.py
rxsci/operators/distinct_until_changed.py
rxsci/operators/do_action.py
rxsci/operators/filter.py
rxsci/operators/first.py
rxsci/operators/flat_map.py
rxsci/operators/from_iterable.py
rxsci/operators/group_by.py
rxsci/operators/identity.py
rxsci/operators/last.py
rxsci/operators/map.py
rxsci/operators/multiplex.py
rxsci/operators/on_subscribe.py
rxsci/operators/pandas.py
rxsci/operators/progress.py
rxsci/operators/scan.py
rxsci/operators/starmap.py
rxsci/operators/start_with.py
rxsci/operators/take.py
rxsci/operators/tee_map.py
rxsci/operators/with_latest_from.py
rxsci/state/__init__.py
rxsci/state/markers.py
rxsci/state/memory_store.py
