Metadata-Version: 2.4
Name: rxsci
Version: 0.32.0
Summary: ReactiveX for data science
Author: Romain Picard
Author-email: romain.picard@oakbits.com
License: MIT License
Project-URL: repository, https://github.com/maki-nage/rxsci.git
Keywords: reactivex,streaming,data-science
Classifier: Development Status :: 4 - Beta
Classifier: License :: OSI Approved :: MIT License
Classifier: Intended Audience :: Developers
Classifier: Programming Language :: Python :: 3
Classifier:   Topic :: Scientific/Engineering :: Artificial Intelligence
Requires-Python: >=3.8
License-File: LICENSE.txt
Requires-Dist: distogram~=3.0
Requires-Dist: python-dateutil~=2.8
Requires-Dist: Rx~=3.2
Requires-Dist: orjson~=3.9; implementation_name == "cpython"
Requires-Dist: zstandard[cffi]==0.23.0
Provides-Extra: test
Requires-Dist: pytest; extra == "test"
Dynamic: license-file
